{"_type":"export","__export_format":4,"__export_date":"2024-08-21T17:33:38.451Z","__export_source":"insomnia.desktop.app:v8.6.1","resources":[{"_id":"req_9139720a5ab44df58245ff4889ae4d10","parentId":"fld_488773f4b0d644678578d46430d80123","modified":1724261553671,"created":1723922356707,"url":"{{ _.api_url }}/user","name":"User","description":"","method":"GET","body":{},"parameters":[],"headers":[{"name":"User-Agent","value":"insomnia/8.6.1","id":"pair_c20bd45a85604bfaa7f3567ecf5f5d2c"},{"id":"pair_da87e90306d546a7a60dc0234102e240","name":"Content-Type","value":"application/json","description":""}],"authentication":{"type":"bearer","token":"{{ _.api_token }}","disabled":false},"metaSortKey":-1724261553620,"isPrivate":false,"pathParameters":[],"settingStoreCookies":true,"settingSendCookies":true,"settingDisableRenderRequestBody":false,"settingEncodeUrl":true,"settingRebuildPath":true,"settingFollowRedirects":"global","_type":"request"},{"_id":"fld_488773f4b0d644678578d46430d80123","parentId":"fld_b5d2faaaa55b4cedb879c4299fbadbc5","modified":1724261538279,"created":1724261538279,"name":"User","description":"","environment":{},"environmentPropertyOrder":null,"metaSortKey":-1724261538279,"_type":"request_group"},{"_id":"fld_b5d2faaaa55b4cedb879c4299fbadbc5","parentId":"wrk_scratchpad","modified":1723922814546,"created":1723918583093,"name":"Propli","description":"","environment":{"api_url":"http://localhost:8989/api","api_token":"{% response 'body', 'req_4911a5b9e31e44d6a3130fad5b435d23', 'b64::JFt0b2tlbl0=::46b', 'never', 60 %}"},"environmentPropertyOrder":{"&":["api_url","api_token"]},"metaSortKey":-1723918583093,"_type":"request_group"},{"_id":"wrk_scratchpad","parentId":null,"modified":1712347691510,"created":1712347691510,"name":"Scratch Pad","description":"","scope":"collection","_type":"workspace"},{"_id":"req_61424e53613748579cc3468309ccffec","parentId":"fld_fa66635f785b42bf842b62757dbcf474","modified":1724261528743,"created":1724261507319,"url":"{{ _.api_url }}/building","name":"index","description":"","method":"GET","body":{},"parameters":[],"headers":[{"name":"User-Agent","value":"insomnia/8.6.1"}],"authentication":{"type":"bearer","token":"{{ _.api_token }}"},"metaSortKey":-1724261507319,"isPrivate":false,"pathParameters":[],"settingStoreCookies":true,"settingSendCookies":true,"settingDisableRenderRequestBody":false,"settingEncodeUrl":true,"settingRebuildPath":true,"settingFollowRedirects":"global","_type":"request"},{"_id":"fld_fa66635f785b42bf842b62757dbcf474","parentId":"fld_b5d2faaaa55b4cedb879c4299fbadbc5","modified":1724261502957,"created":1724261502957,"name":"Building","description":"","environment":{},"environmentPropertyOrder":null,"metaSortKey":-1724261502957,"_type":"request_group"},{"_id":"req_ca2b6648699d4fe79033379089353376","parentId":"fld_e3033f871093497e841939dba51c402b","modified":1724261332225,"created":1724261041166,"url":"{{ _.api_url }}/audit","name":"Index","description":"","method":"GET","body":{},"parameters":[],"headers":[{"name":"User-Agent","value":"insomnia/8.6.1"}],"authentication":{"type":"bearer","token":"{{ _.api_token }}"},"metaSortKey":-1724261041166,"isPrivate":false,"pathParameters":[],"settingStoreCookies":true,"settingSendCookies":true,"settingDisableRenderRequestBody":false,"settingEncodeUrl":true,"settingRebuildPath":true,"settingFollowRedirects":"global","_type":"request"},{"_id":"fld_e3033f871093497e841939dba51c402b","parentId":"fld_b5d2faaaa55b4cedb879c4299fbadbc5","modified":1724261037747,"created":1724261037747,"name":"Audit","description":"","environment":{},"environmentPropertyOrder":null,"metaSortKey":-1724261037747,"_type":"request_group"},{"_id":"req_94fbc02e9a9e47a1b5cc33f7a2bf11cc","parentId":"fld_1cb6826b57804c248342ab4bad751a07","modified":1724120305649,"created":1724093773423,"url":"{{ _.api_url }}/task/comment","name":"Create Comment","description":"","method":"POST","body":{"mimeType":"application/json","text":"{\n\t\"task_id\":1,\n\t\"comment\": \"Testando a Tarefa e finalizando alguns ajustes\"\n}"},"parameters":[],"headers":[{"name":"Content-Type","value":"application/json"},{"name":"User-Agent","value":"insomnia/8.6.1"}],"authentication":{"type":"bearer","token":"{{ _.api_token }}"},"metaSortKey":-1724093773423,"isPrivate":false,"pathParameters":[],"settingStoreCookies":true,"settingSendCookies":true,"settingDisableRenderRequestBody":false,"settingEncodeUrl":true,"settingRebuildPath":true,"settingFollowRedirects":"global","_type":"request"},{"_id":"fld_1cb6826b57804c248342ab4bad751a07","parentId":"fld_b5d2faaaa55b4cedb879c4299fbadbc5","modified":1724093771012,"created":1724093763259,"name":"TaskComment","description":"","environment":{},"environmentPropertyOrder":null,"metaSortKey":-1724093763259,"_type":"request_group"},{"_id":"req_5229dfd4550444e0b5832b0e01219fbf","parentId":"fld_4bfeb98e37c740b7af555e55ea9b623d","modified":1724186556926,"created":1724070108564,"url":"{{ _.api_url }}/task/status","name":"index","description":"","method":"GET","body":{},"parameters":[],"headers":[{"name":"User-Agent","value":"insomnia/8.6.1"}],"authentication":{"type":"bearer","token":"{{ _.api_token }}","disabled":false},"metaSortKey":-1724070108564,"isPrivate":false,"pathParameters":[],"settingStoreCookies":true,"settingSendCookies":true,"settingDisableRenderRequestBody":false,"settingEncodeUrl":true,"settingRebuildPath":true,"settingFollowRedirects":"global","_type":"request"},{"_id":"fld_4bfeb98e37c740b7af555e55ea9b623d","parentId":"fld_b5d2faaaa55b4cedb879c4299fbadbc5","modified":1724070104320,"created":1724070104320,"name":"TaskStatus","description":"","environment":{},"environmentPropertyOrder":null,"metaSortKey":-1724070104320,"_type":"request_group"},{"_id":"req_90110aea080541868bedcd3b5fc0650d","parentId":"fld_f4a25c6bd68c4154916839c04e9bac95","modified":1724173596104,"created":1724033779042,"url":"{{ _.api_url }}/task","name":"Create Task","description":"","method":"POST","body":{"mimeType":"application/json","text":"{\n\t\"task_name\": \"teste\",\n\t\"task_description\": \"Tesde de Description\",\n\t\"assigned_team\": 1,\n\t\"assigned_building\": 1,\n\t\"assigned_user\": 1\n}"},"parameters":[],"headers":[{"name":"Content-Type","value":"application/json"},{"name":"User-Agent","value":"insomnia/8.6.1"}],"authentication":{"type":"bearer","token":"{{ _.api_token }}"},"metaSortKey":-1724033779042,"isPrivate":false,"pathParameters":[],"settingStoreCookies":true,"settingSendCookies":true,"settingDisableRenderRequestBody":false,"settingEncodeUrl":true,"settingRebuildPath":true,"settingFollowRedirects":"global","_type":"request"},{"_id":"fld_f4a25c6bd68c4154916839c04e9bac95","parentId":"fld_b5d2faaaa55b4cedb879c4299fbadbc5","modified":1724033775197,"created":1724033775197,"name":"Task","description":"","environment":{},"environmentPropertyOrder":null,"metaSortKey":-1724033775197,"_type":"request_group"},{"_id":"req_fcb61d6fa0fe412eab71355d506a4b68","parentId":"fld_f4a25c6bd68c4154916839c04e9bac95","modified":1724173488879,"created":1724070649663,"url":"{{ _.api_url }}/task","name":"Update Task","description":"","method":"PUT","body":{"mimeType":"application/json","text":"{\n\t\"task_id\": 1,\n\t\"task_name\": \"teste 3\",\n\t\"task_description\": \"\",\n\t\"assigned_user\": 1,\n\t\"task_status\": 3\n}"},"parameters":[],"headers":[{"name":"Content-Type","value":"application/json"},{"name":"User-Agent","value":"insomnia/8.6.1"}],"authentication":{"type":"bearer","token":"{{ _.api_token }}"},"metaSortKey":-1724032661452,"isPrivate":false,"pathParameters":[],"settingStoreCookies":true,"settingSendCookies":true,"settingDisableRenderRequestBody":false,"settingEncodeUrl":true,"settingRebuildPath":true,"settingFollowRedirects":"global","_type":"request"},{"_id":"req_d64abc9ec9ab46a1a8653ef28a571547","parentId":"fld_f4a25c6bd68c4154916839c04e9bac95","modified":1724172498089,"created":1724120455266,"url":"{{ _.api_url }}/task?task_creation_start=2024-08-19&task_creation_end=2024-08-20","name":"Index","description":"","method":"GET","body":{"mimeType":"application/json","text":""},"parameters":[],"headers":[{"name":"Content-Type","value":"application/json"},{"name":"User-Agent","value":"insomnia/8.6.1"}],"authentication":{"type":"bearer","token":"{{ _.api_token }}"},"metaSortKey":-1724032102657,"isPrivate":false,"pathParameters":[],"settingStoreCookies":true,"settingSendCookies":true,"settingDisableRenderRequestBody":false,"settingEncodeUrl":true,"settingRebuildPath":true,"settingFollowRedirects":"global","_type":"request"},{"_id":"req_67cd927d361a47e19fbdb29b0c64005b","parentId":"fld_ae98028c8f2c49f2a046918edf14bb28","modified":1724031583824,"created":1724031543862,"url":"{{ _.api_url }}/auth/me","name":"Me","description":"","method":"GET","body":{},"parameters":[],"headers":[{"name":"User-Agent","value":"insomnia/8.6.1"}],"authentication":{"type":"bearer","token":"{{ _.api_token }}"},"metaSortKey":-1724031543862,"isPrivate":false,"pathParameters":[],"settingStoreCookies":true,"settingSendCookies":true,"settingDisableRenderRequestBody":false,"settingEncodeUrl":true,"settingRebuildPath":true,"settingFollowRedirects":"global","_type":"request"},{"_id":"fld_ae98028c8f2c49f2a046918edf14bb28","parentId":"fld_b5d2faaaa55b4cedb879c4299fbadbc5","modified":1724031532713,"created":1724031532713,"name":"Auth","description":"","environment":{},"environmentPropertyOrder":null,"metaSortKey":-1724031532713,"_type":"request_group"},{"_id":"req_4911a5b9e31e44d6a3130fad5b435d23","parentId":"fld_ae98028c8f2c49f2a046918edf14bb28","modified":1724184009617,"created":1723918585559,"url":"{{ _.api_url }}/auth","name":"Login","description":"","method":"POST","body":{"mimeType":"application/json","text":"{\n\t\"email\": \"berniece.jones@example.net\",\n\t\"password\": \"password\"\n}"},"parameters":[],"headers":[{"name":"Content-Type","value":"application/json"},{"name":"User-Agent","value":"insomnia/8.6.1"}],"authentication":{},"metaSortKey":-1724031541020,"isPrivate":false,"pathParameters":[],"settingStoreCookies":true,"settingSendCookies":true,"settingDisableRenderRequestBody":false,"settingEncodeUrl":true,"settingRebuildPath":true,"settingFollowRedirects":"global","_type":"request"},{"_id":"req_629d359348504cd7b47e0789e91874eb","parentId":"fld_ae98028c8f2c49f2a046918edf14bb28","modified":1724031616198,"created":1724031602764,"url":"{{ _.api_url }}/auth","name":"Refresh Token","description":"","method":"PUT","body":{"mimeType":"application/json","text":"{\n\t\"email\": \"stanford59@example.org\",\n\t\"password\": \"password\"\n}"},"parameters":[],"headers":[{"name":"Content-Type","value":"application/json"},{"name":"User-Agent","value":"insomnia/8.6.1"}],"authentication":{"type":"bearer","token":"{{ _.api_token }}"},"metaSortKey":-1723976948863.5,"isPrivate":false,"pathParameters":[],"settingStoreCookies":true,"settingSendCookies":true,"settingDisableRenderRequestBody":false,"settingEncodeUrl":true,"settingRebuildPath":true,"settingFollowRedirects":"global","_type":"request"},{"_id":"req_d9e6881090ea487c86f1b02a3cb6cb1d","parentId":"fld_ae98028c8f2c49f2a046918edf14bb28","modified":1724031703149,"created":1724031689602,"url":"{{ _.api_url }}/auth/logout","name":"Logout","description":"","method":"POST","body":{"mimeType":"application/json","text":"{\n\t\"email\": \"stanford59@example.org\",\n\t\"password\": \"password\"\n}"},"parameters":[],"headers":[{"name":"Content-Type","value":"application/json"},{"name":"User-Agent","value":"insomnia/8.6.1"}],"authentication":{"type":"bearer","token":"{{ _.api_token }}"},"metaSortKey":-1723949652785.25,"isPrivate":false,"pathParameters":[],"settingStoreCookies":true,"settingSendCookies":true,"settingDisableRenderRequestBody":false,"settingEncodeUrl":true,"settingRebuildPath":true,"settingFollowRedirects":"global","_type":"request"},{"_id":"env_99d30891da4bdcebc63947a8fc17f076de878684","parentId":"wrk_scratchpad","modified":1712347713490,"created":1712347713490,"name":"Base Environment","data":{},"dataPropertyOrder":null,"color":null,"isPrivate":false,"metaSortKey":1712347713490,"_type":"environment"},{"_id":"jar_99d30891da4bdcebc63947a8fc17f076de878684","parentId":"wrk_scratchpad","modified":1724123820301,"created":1712347713607,"name":"Default Jar","cookies":[{"key":"XSRF-TOKEN","value":"eyJpdiI6IjVUdlV2NjBuRkxOd1hBSmM0TlIweHc9PSIsInZhbHVlIjoiNGNGajc3NS9OTE93U1BaMFRxWWdNQ2Z1Vk0zVmw0aDlvR2pXK1hldkdobGVTcnU2SERnZXRzd3JTUEo5dEI0VHM0cUoram1ub0RYUjc1dWQwdmRiU3NJdnJpNGQxcW9nVzFmaTF3TmpkbTRSdE1CZis1cmk4bEtBMXgrdXlIMTYiLCJtYWMiOiI1YjU4NzdlNjNjZmU5MWEwN2I5ZWJkNDFhNWQ4NGMxMWVlNzNjYWE5ZDY3MGI0ZmRjOTllNWIwNGEwMWIyNzVhIiwidGFnIjoiIn0%3D","expires":"2024-08-20T05:17:00.000Z","maxAge":7200,"domain":"localhost","path":"/","hostOnly":true,"creation":"2024-08-19T02:16:51.873Z","lastAccessed":"2024-08-20T03:17:00.301Z","sameSite":"lax","id":"9e0c54de-3463-49dc-b0b9-f3f6683273c5"},{"key":"laravel_session","value":"eyJpdiI6ImJ2ZjcwWGJITXovZG9Fc09SQXllWFE9PSIsInZhbHVlIjoiY2tsMXZ4cGVKYWF4TkViTXBMVkpzRzREWmFmemd2bkhGQnFkbnNzMG5qa0k4VjZFTWdrTnVxTC9DdENyc3VmQnBMMUJ5dVRVUG0ybjVDaXBWL2Z6TlBvUlpVWEhubWU0LzZBWVNhR1gyc2dLbDFaZFdmb29BZDNFMlZqU1BmeXAiLCJtYWMiOiJjYjhmNTNjZWQwZDhiMjE4NTMzNzdmYzU3NWU5NzRmZWY3YWU0YTMxOWJiYjc5OWMzM2Y5ZmZjMDgwOTFlYTVkIiwidGFnIjoiIn0%3D","expires":"2024-08-20T05:17:00.000Z","maxAge":7200,"domain":"localhost","path":"/","httpOnly":true,"hostOnly":true,"creation":"2024-08-19T02:16:51.874Z","lastAccessed":"2024-08-20T03:17:00.301Z","sameSite":"lax","id":"2f8b4830-7092-4121-95e3-fe56fb11d1ef"}],"_type":"cookie_jar"}]}